README.rst
setup.py
bin/shuttertalk
dtwNonsense.egg-info/PKG-INFO
dtwNonsense.egg-info/SOURCES.txt
dtwNonsense.egg-info/dependency_links.txt
dtwNonsense.egg-info/requires.txt
dtwNonsense.egg-info/top_level.txt
shuttertalk/__init__.py