Metadata-Version: 1.0
Name: dtwNonsense
Version: 0.1.2
Summary: something
Home-page: http://jhjameshuang.com
Author: James
Author-email: jjh568@nyu.edu
License: GPL
Platform: UNKNOWN
